{".class": "MypyFile", "_fullname": "allentune.executors.ray_executor", "is_partial_stub_package": false, "is_stub": false, "names": {".class": "SymbolTable", "Any": {".class": "SymbolTableNode", "cross_ref": "typing.Any", "kind": "Gdef"}, "Callable": {".class": "SymbolTableNode", "cross_ref": "typing.Callable", "kind": "Gdef"}, "Dict": {".class": "SymbolTableNode", "cross_ref": "typing.Dict", "kind": "Gdef"}, "Executor": {".class": "SymbolTableNode", "cross_ref": "allentune.executors.executor.Executor", "kind": "Gdef"}, "MedianStoppingRule": {".class": "SymbolTableNode", "kind": "Gdef", "node": {".class": "Var", "flags": ["is_suppressed_import"], "fullname": "allentune.executors.ray_executor.MedianStoppingRule", "name": "MedianStoppingRule", "type": {".class": "AnyType", "missing_import_name": "allentune.executors.ray_executor.MedianStoppingRule", "source_any": null, "type_of_any": 3}}}, "Optional": {".class": "SymbolTableNode", "cross_ref": "typing.Optional", "kind": "Gdef"}, "RandomSearch": {".class": "SymbolTableNode", "cross_ref": "allentune.util.random_search.RandomSearch", "kind": "Gdef"}, "RayExecutor": {".class": "SymbolTableNode", "kind": "Gdef", "node": {".class": "TypeInfo", "_promote": null, "abstract_attributes": [], "bases": ["allentune.executors.executor.Executor"], "declared_metaclass": null, "defn": {".class": "ClassDef", "fullname": "allentune.executors.ray_executor.RayExecutor", "name": "RayExecutor", "type_vars": []}, "flags": [], "fullname": "allentune.executors.ray_executor.RayExecutor", "metaclass_type": "abc.ABCMeta", "metadata": {}, "module_name": "allentune.executors.ray_executor", "mro": ["allentune.executors.ray_executor.RayExecutor", "allentune.executors.executor.Executor", "abc.ABC", "builtins.object"], "names": {".class": "SymbolTable", "__init__": {".class": "SymbolTableNode", "kind": "Mdef", "node": {".class": "FuncDef", "arg_kinds": [0, 0], "arg_names": ["self", "runner"], "flags": [], "fullname": "allentune.executors.ray_executor.RayExecutor.__init__", "name": "__init__", "type": {".class": "CallableType", "arg_kinds": [0, 0], "arg_names": ["self", "runner"], "arg_types": ["allentune.executors.ray_executor.RayExecutor", "allentune.runners.runner.Runner"], "bound_args": [], "def_extras": {"first_arg": "self"}, "fallback": "builtins.function", "implicit": false, "is_ellipsis_args": false, "name": "__init__ of RayExecutor", "ret_type": {".class": "NoneTyp"}, "variables": []}}}, "default_argument_parser": {".class": "SymbolTableNode", "kind": "Mdef", "node": {".class": "FuncDef", "arg_kinds": [0], "arg_names": ["self"], "flags": [], "fullname": "allentune.executors.ray_executor.RayExecutor.default_argument_parser", "name": "default_argument_parser", "type": null}}, "name": {".class": "SymbolTableNode", "kind": "Mdef", "node": {".class": "Var", "flags": ["is_initialized_in_class"], "fullname": "allentune.executors.ray_executor.RayExecutor.name", "name": "name", "type": "builtins.str"}}, "parse_search_config": {".class": "SymbolTableNode", "kind": "Mdef", "node": {".class": "FuncDef", "arg_kinds": [0, 0], "arg_names": ["self", "search_config"], "flags": [], "fullname": "allentune.executors.ray_executor.RayExecutor.parse_search_config", "name": "parse_search_config", "type": {".class": "CallableType", "arg_kinds": [0, 0], "arg_names": ["self", "search_config"], "arg_types": ["allentune.executors.ray_executor.RayExecutor", {".class": "Instance", "args": [{".class": "AnyType", "missing_import_name": null, "source_any": null, "type_of_any": 4}, {".class": "AnyType", "missing_import_name": null, "source_any": null, "type_of_any": 4}], "type_ref": "builtins.dict"}], "bound_args": [], "def_extras": {"first_arg": "self"}, "fallback": "builtins.function", "implicit": false, "is_ellipsis_args": false, "name": "parse_search_config of RayExecutor", "ret_type": {".class": "Instance", "args": [{".class": "AnyType", "missing_import_name": null, "source_any": null, "type_of_any": 4}, {".class": "AnyType", "missing_import_name": null, "source_any": null, "type_of_any": 4}], "type_ref": "builtins.dict"}, "variables": []}}}, "run_distributed": {".class": "SymbolTableNode", "kind": "Mdef", "node": {".class": "FuncDef", "arg_kinds": [0, 0, 0, 1], "arg_names": ["self", "run_func", "default_args", "run_args"], "flags": [], "fullname": "allentune.executors.ray_executor.RayExecutor.run_distributed", "name": "run_distributed", "type": {".class": "CallableType", "arg_kinds": [0, 0, 0, 1], "arg_names": ["self", "run_func", "default_args", "run_args"], "arg_types": ["allentune.executors.ray_executor.RayExecutor", {".class": "CallableType", "arg_kinds": [0, 0], "arg_names": [null, null], "arg_types": [{".class": "Instance", "args": ["builtins.str", {".class": "AnyType", "missing_import_name": null, "source_any": null, "type_of_any": 2}], "type_ref": "builtins.dict"}, {".class": "AnyType", "missing_import_name": "allentune.executors.ray_executor.StatusReporter", "source_any": null, "type_of_any": 3}], "bound_args": [], "def_extras": {}, "fallback": "builtins.function", "implicit": false, "is_ellipsis_args": false, "name": null, "ret_type": {".class": "NoneTyp"}, "variables": []}, "argparse.Namespace", {".class": "UnionType", "items": ["argparse.Namespace", {".class": "NoneTyp"}]}], "bound_args": [], "def_extras": {"first_arg": "self"}, "fallback": "builtins.function", "implicit": false, "is_ellipsis_args": false, "name": "run_distributed of RayExecutor", "ret_type": {".class": "NoneTyp"}, "variables": []}}}}, "tuple_type": null, "type_vars": [], "typeddict_type": null}}, "Runner": {".class": "SymbolTableNode", "cross_ref": "allentune.runners.runner.Runner", "kind": "Gdef"}, "StatusReporter": {".class": "SymbolTableNode", "kind": "Gdef", "node": {".class": "Var", "flags": ["is_suppressed_import"], "fullname": "allentune.executors.ray_executor.StatusReporter", "name": "StatusReporter", "type": {".class": "AnyType", "missing_import_name": "allentune.executors.ray_executor.StatusReporter", "source_any": null, "type_of_any": 3}}}, "__doc__": {".class": "SymbolTableNode", "kind": "Gdef", "node": {".class": "Var", "flags": [], "fullname": "allentune.executors.ray_executor.__doc__", "name": "__doc__", "type": "builtins.str"}}, "__file__": {".class": "SymbolTableNode", "kind": "Gdef", "node": {".class": "Var", "flags": [], "fullname": "allentune.executors.ray_executor.__file__", "name": "__file__", "type": "builtins.str"}}, "__name__": {".class": "SymbolTableNode", "kind": "Gdef", "node": {".class": "Var", "flags": [], "fullname": "allentune.executors.ray_executor.__name__", "name": "__name__", "type": "builtins.str"}}, "__package__": {".class": "SymbolTableNode", "kind": "Gdef", "node": {".class": "Var", "flags": [], "fullname": "allentune.executors.ray_executor.__package__", "name": "__package__", "type": "builtins.str"}}, "argparse": {".class": "SymbolTableNode", "cross_ref": "argparse", "kind": "Gdef"}, "function": {".class": "SymbolTableNode", "kind": "Gdef", "node": {".class": "Var", "flags": ["is_suppressed_import"], "fullname": "allentune.executors.ray_executor.function", "name": "function", "type": {".class": "AnyType", "missing_import_name": "allentune.executors.ray_executor.function", "source_any": null, "type_of_any": 3}}}, "json": {".class": "SymbolTableNode", "cross_ref": "json", "kind": "Gdef"}, "logger": {".class": "SymbolTableNode", "kind": "Gdef", "node": {".class": "Var", "flags": [], "fullname": "allentune.executors.ray_executor.logger", "name": "logger", "type": "logging.Logger"}}, "logging": {".class": "SymbolTableNode", "cross_ref": "logging", "kind": "Gdef"}, "np": {".class": "SymbolTableNode", "kind": "Gdef", "node": {".class": "Var", "flags": ["is_suppressed_import"], "fullname": "allentune.executors.ray_executor.np", "name": "np", "type": {".class": "AnyType", "missing_import_name": "allentune.executors.ray_executor.np", "source_any": null, "type_of_any": 3}}}, "os": {".class": "SymbolTableNode", "cross_ref": "os", "kind": "Gdef"}, "random": {".class": "SymbolTableNode", "cross_ref": "random", "kind": "Gdef"}, "ray": {".class": "SymbolTableNode", "kind": "Gdef", "node": {".class": "Var", "flags": ["is_suppressed_import"], "fullname": "allentune.executors.ray_executor.ray", "name": "ray", "type": {".class": "AnyType", "missing_import_name": "allentune.executors.ray_executor.ray", "source_any": null, "type_of_any": 3}}}, "register_trainable": {".class": "SymbolTableNode", "kind": "Gdef", "node": {".class": "Var", "flags": ["is_suppressed_import"], "fullname": "allentune.executors.ray_executor.register_trainable", "name": "register_trainable", "type": {".class": "AnyType", "missing_import_name": "allentune.executors.ray_executor.register_trainable", "source_any": null, "type_of_any": 3}}}, "run_experiments": {".class": "SymbolTableNode", "kind": "Gdef", "node": {".class": "Var", "flags": ["is_suppressed_import"], "fullname": "allentune.executors.ray_executor.run_experiments", "name": "run_experiments", "type": {".class": "AnyType", "missing_import_name": "allentune.executors.ray_executor.run_experiments", "source_any": null, "type_of_any": 3}}}, "sample_from": {".class": "SymbolTableNode", "kind": "Gdef", "node": {".class": "Var", "flags": ["is_suppressed_import"], "fullname": "allentune.executors.ray_executor.sample_from", "name": "sample_from", "type": {".class": "AnyType", "missing_import_name": "allentune.executors.ray_executor.sample_from", "source_any": null, "type_of_any": 3}}}}, "path": "/Users/suching/Github/allentune/allentune/executors/ray_executor.py"}